baidu_serp_api/__init__.py
baidu_serp_api/baidu_mobile.py
baidu_serp_api/baidu_pc.py
baidu_serp_api/util.py
baidu_serp_api-1.1.7.dist-info/LICENSE.txt
baidu_serp_api-1.1.7.dist-info/METADATA
baidu_serp_api-1.1.7.dist-info/WHEEL
baidu_serp_api-1.1.7.dist-info/top_level.txt
baidu_serp_api-1.1.7.dist-info/RECORD
