Metadata-Version: 2.1
Name: baidu-serp-api
Version: 1.1.7
Summary: A library to extract data from Baidu SERP and output it as JSON objects
Author-email: Ben Chen <chan@live.cn>
License: GPL-3.0
Project-URL: Homepage, https://github.com/ohblue/baidu-serp-api
Project-URL: Repository, https://github.com/ohblue/baidu-serp-api
Project-URL: Issues, https://github.com/ohblue/baidu-serp-api/issues
Keywords: baidu,serp,search,scraping,json
Classifier: Programming Language :: Python :: 3
Classifier: Programming Language :: Python :: 3.12
Classifier: Programming Language :: Python :: 3.13
Classifier: License :: OSI Approved :: GNU General Public License v3 (GPLv3)
Classifier: Operating System :: OS Independent
Classifier: Development Status :: 4 - Beta
Classifier: Intended Audience :: Developers
Classifier: Topic :: Internet :: WWW/HTTP :: Dynamic Content
Classifier: Topic :: Software Development :: Libraries :: Python Modules
Classifier: Topic :: Text Processing :: Markup :: HTML
Requires-Python: >=3.12
License-File: LICENSE.txt
Requires-Dist: requests
Requires-Dist: beautifulsoup4
Requires-Dist: loguru
Requires-Dist: certifi
Requires-Dist: brotli
Provides-Extra: dev
Requires-Dist: pytest; extra == "dev"
Requires-Dist: pytest-cov; extra == "dev"
